odoo/addons/l10n_ec_base/README.rst
odoo/addons/l10n_ec_base/__init__.py
odoo/addons/l10n_ec_base/__manifest__.py
odoo/addons/l10n_ec_base/data/account_tax_data.py
odoo/addons/l10n_ec_base/data/account_tax_group_data.py
odoo/addons/l10n_ec_base/data/template/account.journal-ec.csv
odoo/addons/l10n_ec_base/data/template/account.tax-ec.csv
odoo/addons/l10n_ec_base/i18n/es.po
odoo/addons/l10n_ec_base/i18n/l10n_ec_base.pot
odoo/addons/l10n_ec_base/models/__init__.py
odoo/addons/l10n_ec_base/models/account_chart_template.py
odoo/addons/l10n_ec_base/models/account_fiscal_position.py
odoo/addons/l10n_ec_base/models/account_journal.py
odoo/addons/l10n_ec_base/models/account_payment.py
odoo/addons/l10n_ec_base/models/account_tax.py
odoo/addons/l10n_ec_base/models/res_company.py
odoo/addons/l10n_ec_base/models/res_partner.py
odoo/addons/l10n_ec_base/readme/CONTRIBUTORS.md
odoo/addons/l10n_ec_base/readme/DESCRIPTION.md
odoo/addons/l10n_ec_base/readme/USAGE.md
odoo/addons/l10n_ec_base/static/description/icon.png
odoo/addons/l10n_ec_base/static/description/index.html
odoo/addons/l10n_ec_base/tests/__init__.py
odoo/addons/l10n_ec_base/tests/test_account_journal.py
odoo/addons/l10n_ec_base/tests/test_account_payment.py
odoo/addons/l10n_ec_base/tests/test_res_partner.py
odoo/addons/l10n_ec_base/views/account_fiscal_position_view.xml
odoo/addons/l10n_ec_base/views/account_journal_view.xml
odoo/addons/l10n_ec_base/views/account_payment_view.xml
odoo/addons/l10n_ec_base/views/account_tax_view.xml
odoo/addons/l10n_ec_base/views/res_company_view.xml
odoo/addons/l10n_ec_base/views/res_partner_view.xml
odoo/addons/l10n_ec_base/wizard/__init__.py
odoo/addons/l10n_ec_base/wizard/account_payment_register.py
odoo/addons/l10n_ec_base/wizard/account_payment_register_views.xml
odoo_addon_l10n_ec_base-18.0.1.0.0.2.dist-info/METADATA
odoo_addon_l10n_ec_base-18.0.1.0.0.2.dist-info/WHEEL
odoo_addon_l10n_ec_base-18.0.1.0.0.2.dist-info/top_level.txt
odoo_addon_l10n_ec_base-18.0.1.0.0.2.dist-info/RECORD
