Metadata-Version: 2.1
Name: odoo-addon-l10n_ec_base
Version: 18.0.1.0.0.2
Requires-Python: >=3.10
Requires-Dist: odoo==18.0.*
Summary: Ecuadorian Localization
Home-page: https://github.com/OCA/l10n-ecuador
License: AGPL-3
Author: Odoo Community Association (OCA)
Author-email: support@odoo-community.org
Classifier: Programming Language :: Python
Classifier: Framework :: Odoo
Classifier: Framework :: Odoo :: 18.0
Classifier: License :: OSI Approved :: GNU Affero General Public License v3
